treetime/CLI_io.py
treetime/__init__.py
treetime/__main__.py
treetime/aa_models.py
treetime/arg.py
treetime/argument_parser.py
treetime/branch_len_interpolator.py
treetime/clock_filter_methods.py
treetime/clock_tree.py
treetime/config.py
treetime/distribution.py
treetime/gtr.py
treetime/gtr_site_specific.py
treetime/merger_models.py
treetime/node_interpolator.py
treetime/nuc_models.py
treetime/seq_utils.py
treetime/seqgen.py
treetime/sequence_data.py
treetime/treeanc.py
treetime/treeregression.py
treetime/treetime.py
treetime/utils.py
treetime/vcf_utils.py
treetime/wrappers.py
phylo_treetime-0.11.4.dist-info/LICENSE
phylo_treetime-0.11.4.dist-info/METADATA
phylo_treetime-0.11.4.dist-info/WHEEL
phylo_treetime-0.11.4.dist-info/entry_points.txt
phylo_treetime-0.11.4.dist-info/top_level.txt
phylo_treetime-0.11.4.dist-info/RECORD
