Metadata-Version: 2.1
Name: phylo-treetime
Version: 0.11.4
Summary: Maximum-likelihood phylodynamic inference
Home-page: https://github.com/neherlab/treetime
Author: Pavel Sagulenko, Emma Hodcroft, and Richard Neher
Author-email: richard.neher@unibas.ch
License: MIT
Keywords: Time-stamped phylogenies,phylogeography,virus evolution
Classifier: Development Status :: 5 - Production/Stable
Classifier: Topic :: Scientific/Engineering :: Bio-Informatics
Classifier: License :: OSI Approved :: MIT License
Classifier: Programming Language :: Python :: 3.7
Classifier: Programming Language :: Python :: 3.8
Classifier: Programming Language :: Python :: 3.9
Classifier: Programming Language :: Python :: 3.10
License-File: LICENSE
Requires-Dist: biopython !=1.77,!=1.78,>=1.67
Requires-Dist: numpy >=1.10.4
Requires-Dist: pandas >=0.17.1
Requires-Dist: scipy >=0.16.1
Requires-Dist: matplotlib >=2.0 ; python_version >= "3.6"
